module/__init__.py
module/add.py
tpdapi-0.0.1.dist-info/METADATA
tpdapi-0.0.1.dist-info/WHEEL
tpdapi-0.0.1.dist-info/top_level.txt
tpdapi-0.0.1.dist-info/RECORD
